async4jsonrpc/__init__.py
async4jsonrpc/client.py
async4jsonrpc/comm.py
async4jsonrpc/server.py
async4jsonrpc-1.0.0.dist-info/LICENSE
async4jsonrpc-1.0.0.dist-info/METADATA
async4jsonrpc-1.0.0.dist-info/WHEEL
async4jsonrpc-1.0.0.dist-info/top_level.txt
async4jsonrpc-1.0.0.dist-info/RECORD
