Metadata-Version: 2.1
Name: async4jsonrpc
Version: 1.0.0
Summary: async4jsonrpc: Asynchronous python module for JSON-RPC
Home-page: https://github.com/shigebeyond/async4jsonrpc
Author: shigebeyond
Author-email: 772910474@qq.com
License: BSD
Classifier: Development Status :: 5 - Production/Stable
Classifier: Topic :: Software Development :: Libraries :: Python Modules
Classifier: Operating System :: POSIX :: Linux
Classifier: Operating System :: MacOS :: MacOS X
Classifier: Operating System :: Microsoft :: Windows
Classifier: Programming Language :: Python
Classifier: Programming Language :: Python :: 3.7
Classifier: Programming Language :: Python :: 3.8
Classifier: Programming Language :: Python :: 3.9
Requires-Python: >=3.6
License-File: LICENSE
Requires-Dist: pyutilb (>=1.0.8)
Requires-Dist: jsonpickle (>=3.0.4)
